README
setup.py
quix/__init__.py
quix.pay.egg-info/PKG-INFO
quix.pay.egg-info/SOURCES.txt
quix.pay.egg-info/dependency_links.txt
quix.pay.egg-info/namespace_packages.txt
quix.pay.egg-info/requires.txt
quix.pay.egg-info/top_level.txt
quix/pay/__init__.py
quix/pay/exceptions.py
quix/pay/transaction.py
quix/pay/gateway/__init__.py
quix/pay/gateway/authorizenet.py
quix/pay/gateway/base.py
quix/pay/gateway/psigate.py
quix/pay/gateway/quantam.py