Metadata-Version: 1.0
Name: quix.pay
Version: 0.1.0
Summary: Abstract interfacing with online payment gateways.
Home-page: http://www.quixotix.com
Author: Micah Carrick, Don Morris
Author-email: software@quixotix.com
License: BSD
Keywords: payment gateway processor credit card authorize.net AIM paypal
Platform: UNKNOWN
Classifier: Development Status :: 4 - Beta
Classifier: Environment :: Web Environment
Classifier: Intended Audience :: Developers
Classifier: Operating System :: OS Independent
Classifier: Programming Language :: Python
Classifier: Topic :: Office/Business :: Financial
Classifier: Topic :: Software Development :: Libraries 
